simplebot_howdoi.py
simplebot_howdoi-1.1.2.dist-info/LICENSE
simplebot_howdoi-1.1.2.dist-info/METADATA
simplebot_howdoi-1.1.2.dist-info/WHEEL
simplebot_howdoi-1.1.2.dist-info/entry_points.txt
simplebot_howdoi-1.1.2.dist-info/top_level.txt
simplebot_howdoi-1.1.2.dist-info/RECORD
