Metadata-Version: 2.1
Name: simplebot-howdoi
Version: 1.1.2
Summary: Instant programming answers plugin for SimpleBot.
Home-page: https://github.com/adbenitez/simplebot_howdoi
Author: adbenitez
Author-email: adbenitez@nauta.cu
License: MPL
Keywords: simplebot plugin deltachat
Classifier: Development Status :: 4 - Beta
Classifier: Environment :: Plugins
Classifier: Programming Language :: Python :: 3
Classifier: License :: OSI Approved :: Mozilla Public License 2.0 (MPL 2.0)
Classifier: Operating System :: OS Independent
Classifier: Topic :: Utilities
License-File: LICENSE
Requires-Dist: simplebot >=2.4.0
Requires-Dist: howdoi >=2.0.19
Provides-Extra: dev
Requires-Dist: simplebot >=2.4.0 ; extra == 'dev'
Requires-Dist: howdoi >=2.0.19 ; extra == 'dev'
Requires-Dist: pytest >=6.2.5 ; extra == 'dev'
Requires-Dist: black >=21.12b0 ; extra == 'dev'
Requires-Dist: mypy >=0.930 ; extra == 'dev'
Requires-Dist: isort >=5.10.1 ; extra == 'dev'
Requires-Dist: pylint >=2.12.2 ; extra == 'dev'
Requires-Dist: pylama >=8.3.6 ; extra == 'dev'
Requires-Dist: types-pkg-resources >=0.1.3 ; extra == 'dev'
Provides-Extra: test
Requires-Dist: pytest >=6.2.5 ; extra == 'test'
